dspy_toon/__init__.py
dspy_toon/adapter.py
dspy_toon/py.typed
dspy_toon/streaming.py
dspy_toon/toon.py
dspy_toon-0.1.0.dist-info/METADATA
dspy_toon-0.1.0.dist-info/WHEEL
dspy_toon-0.1.0.dist-info/RECORD
