Metadata-Version: 2.4
Name: dspy-toon
Version: 0.1.0
Summary: DSPy adapter using TOON (Token-Oriented Object Notation) format for 30-60% token reduction in LLM structured outputs
Project-URL: Homepage, https://github.com/Archelunch/dspy-toon
Project-URL: Repository, https://github.com/Archelunch/dspy-toon
Project-URL: Documentation, https://github.com/Archelunch/dspy-toon#readme
Project-URL: Bug Tracker, https://github.com/Archelunch/dspy-toon/issues
Author-email: Archelunch <archelunch@example.com>
License: MIT
Keywords: adapter,ai,dspy,llm,machine-learning,serialization,structured-output,token-efficient,toon
Classifier: Development Status :: 4 - Beta
Classifier: Intended Audience :: Developers
Classifier: Intended Audience :: Science/Research
Classifier: License :: OSI Approved :: MIT License
Classifier: Programming Language :: Python :: 3
Classifier: Programming Language :: Python :: 3.10
Classifier: Programming Language :: Python :: 3.11
Classifier: Programming Language :: Python :: 3.12
Classifier: Programming Language :: Python :: 3.13
Classifier: Programming Language :: Python :: 3.14
Classifier: Topic :: Scientific/Engineering :: Artificial Intelligence
Classifier: Topic :: Software Development :: Libraries :: Python Modules
Classifier: Typing :: Typed
Requires-Python: <3.15,>=3.10
Requires-Dist: datasets>=4.4.1
Requires-Dist: dspy>=2.5.0
Requires-Dist: pydantic>=2.0.0
Provides-Extra: all
Requires-Dist: datasets>=2.0.0; extra == 'all'
Requires-Dist: mypy>=1.8.0; extra == 'all'
Requires-Dist: pandas>=2.0.0; extra == 'all'
Requires-Dist: pytest-asyncio>=0.23.0; extra == 'all'
Requires-Dist: pytest-cov>=4.1.0; extra == 'all'
Requires-Dist: pytest>=8.0.0; extra == 'all'
Requires-Dist: ruff>=0.8.0; extra == 'all'
Requires-Dist: tabulate>=0.9.0; extra == 'all'
Requires-Dist: tiktoken>=0.4.0; extra == 'all'
Provides-Extra: benchmark
Requires-Dist: datasets>=2.0.0; extra == 'benchmark'
Requires-Dist: pandas>=2.0.0; extra == 'benchmark'
Requires-Dist: tabulate>=0.9.0; extra == 'benchmark'
Requires-Dist: tiktoken>=0.4.0; extra == 'benchmark'
Provides-Extra: dev
Requires-Dist: mypy>=1.8.0; extra == 'dev'
Requires-Dist: pytest-asyncio>=0.23.0; extra == 'dev'
Requires-Dist: pytest-cov>=4.1.0; extra == 'dev'
Requires-Dist: pytest>=8.0.0; extra == 'dev'
Requires-Dist: ruff>=0.8.0; extra == 'dev'
